{
  "exe": "/Users/alex/Work/Programs/nnlojet_release/install/bin/NNLOJET",
  "mode": 1,
  "policy": 1,
  "policy_settings": {
    "max_runtime": 300.0
  },
  "ncall": 500,
  "niter": 2,
  "input_files": [
    "job.run"
  ],
  "output_files": [
    "HJJ.HJJ_LO.y1.00E-10.LO_channels",
    "HJJ.HJJ_LO.y1.00E-10.LO_channels.txt",
    "job.s1.out",
    "HJJ.HJJ_LO.s1.log",
    "HJJ.HJJ_LO.y1.00E-10.LO",
    "HJJ.HJJ_LO.y1.00E-10.LO_iterations.txt",
    "job.s1.err"
  ],
  "jobs": {
    "12": {
      "seed": 1,
      "iterations": [
        {
          "iteration": 1,
          "result": -0.0088240822,
          "result_acc": -0.0088240822,
          "error": 0.0058197783,
          "error_acc": 0.0058197783,
          "chi2dof": 8.882e-14
        },
        {
          "iteration": 2,
          "result": -0.0028345268,
          "result_acc": -0.0041887322,
          "error": 0.0031456287,
          "error_acc": 0.0027672693,
          "chi2dof": 0.8116
        }
      ],
      "elapsed_time": 0.096,
      "result": -0.0041887322,
      "error": 0.0027672693,
      "chi2dof": 0.8116
    }
  }
}