{
  "exe": "/Users/alex/Work/Programs/nnlojet_release/install/bin/NNLOJET",
  "mode": 1,
  "policy": 1,
  "policy_settings": {
    "max_runtime": 300.0
  },
  "ncall": 2000,
  "niter": 2,
  "input_files": [
    "job.run",
    "HJJ.HJJ_LO2.y1.00E-10.LO_channels.txt",
    "HJJ.HJJ_LO2.y1.00E-10.LO",
    "HJJ.HJJ_LO2.y1.00E-10.LO_channels",
    "HJJ.HJJ_LO2.y1.00E-10.LO_iterations.txt"
  ],
  "output_files": [
    "HJJ.HJJ_LO2.s2.log",
    "HJJ.HJJ_LO2.y1.00E-10.LO_channels.txt",
    "HJJ.HJJ_LO2.y1.00E-10.LO",
    "HJJ.HJJ_LO2.y1.00E-10.LO_channels",
    "job.s2.out",
    "HJJ.HJJ_LO2.y1.00E-10.LO_iterations.txt",
    "job.s2.err"
  ],
  "jobs": {
    "14": {
      "seed": 2,
      "iterations": [
        {
          "iteration": 1,
          "result": 0.21200129,
          "result_acc": 0.21200129,
          "error": 0.051563374,
          "error_acc": 0.051563374,
          "chi2dof": 0.0
        },
        {
          "iteration": 2,
          "result": 0.52371205,
          "result_acc": 0.22424747,
          "error": 0.25498443,
          "error_acc": 0.05054034,
          "chi2dof": 1.422
        }
      ],
      "elapsed_time": 0.215,
      "result": 0.22424747,
      "error": 0.05054034,
      "chi2dof": 1.422
    }
  }
}